{
  "_class": "shapePath",
  "booleanOperation": 0,
  "do_objectID": "242B3EE9-C058-4C7B-B80A-DFE006F0EDEC",
  "edited": true,
  "exportOptions": {
    "_class": "exportOptions",
    "do_objectID": "82102280-9761-4E2F-91BB-384C688A0A17",
    "exportFormats": [
    ],
    "includedLayerIds": [
    ],
    "layerOptions": 0,
    "shouldTrim": false
  },
  "frame": {
    "_class": "rect",
    "constrainProportions": false,
    "do_objectID": "A8C1CAD6-1E6F-4B58-8FBC-1C4D5A1C97CB",
    "height": 14,
    "width": 19,
    "x": 2,
    "y": 2
  },
  "isClosed": true,
  "isFixedToViewport": false,
  "isFlippedHorizontal": false,
  "isFlippedVertical": false,
  "isLocked": false,
  "isVisible": true,
  "layerListExpandedType": 0,
  "name": "Rectangle 10",
  "nameIsFixed": false,
  "pointRadiusBehaviour": 1,
  "points": [
    {
      "_class": "curvePoint",
      "cornerRadius": 0,
      "curveFrom": "{0, 0.33333333333333331}",
      "curveMode": 1,
      "curveTo": "{0, 0}",
      "hasCurveFrom": false,
      "hasCurveTo": false,
      "point": "{0, 0}"
    },
    {
      "_class": "curvePoint",
      "cornerRadius": 0,
      "curveFrom": "{0, 1.0470588235294114}",
      "curveMode": 1,
      "curveTo": "{0, 0.66666666666666663}",
      "hasCurveFrom": false,
      "hasCurveTo": false,
      "point": "{0, 1}"
    },
    {
      "_class": "curvePoint",
      "cornerRadius": 0,
      "curveFrom": "{0.24703725038998317, 0.68959716951910222}",
      "curveMode": 1,
      "curveTo": "{0.23999999999999999, 0.63529411764706023}",
      "hasCurveFrom": false,
      "hasCurveTo": false,
      "point": "{0.23999999999999999, 0.68235294117647227}"
    },
    {
      "_class": "curvePoint",
      "cornerRadius": 0,
      "curveFrom": "{0.36439132103856486, 0.75746165401031285}",
      "curveMode": 1,
      "curveTo": "{0.21846582181853638, 0.6072442283426317}",
      "hasCurveFrom": false,
      "hasCurveTo": false,
      "point": "{0.29142857142855066, 0.68235294117647227}"
    },
    {
      "_class": "curvePoint",
      "cornerRadius": 0,
      "curveFrom": "{0.72281940468889627, 0.70480220339646471}",
      "curveMode": 1,
      "curveTo": "{0.40703725038998578, 0.81962812927142248}",
      "hasCurveFrom": false,
      "hasCurveTo": false,
      "point": "{0.47999999999999998, 0.89473684210526316}"
    },
    {
      "_class": "curvePoint",
      "cornerRadius": 0,
      "curveFrom": "{0.78053539446966247, 0.53907051641615689}",
      "curveMode": 1,
      "curveTo": "{0.52860916673965053, 0.71934640341468103}",
      "hasCurveFrom": false,
      "hasCurveTo": false,
      "point": "{0.77142857142854637, 0.52941176470588192}"
    },
    {
      "_class": "curvePoint",
      "cornerRadius": 0,
      "curveFrom": "{0.86803603410171259, 0.58641967966227371}",
      "curveMode": 1,
      "curveTo": "{0.80517889124457165, 0.51975301299560694}",
      "hasCurveFrom": false,
      "hasCurveTo": false,
      "point": "{0.81428571428568797, 0.52941176470588192}"
    },
    {
      "_class": "curvePoint",
      "cornerRadius": 0,
      "curveFrom": "{1, 0.7294117647058771}",
      "curveMode": 1,
      "curveTo": "{0.94624968018397548, 0.67240384974948531}",
      "hasCurveFrom": false,
      "hasCurveTo": false,
      "point": "{1, 0.7294117647058771}"
    },
    {
      "_class": "curvePoint",
      "cornerRadius": 0,
      "curveFrom": "{1, 0}",
      "curveMode": 1,
      "curveTo": "{1, 0}",
      "hasCurveFrom": false,
      "hasCurveTo": false,
      "point": "{1, 0}"
    }
  ],
  "resizingConstraint": 63,
  "resizingType": 0,
  "rotation": 0,
  "shouldBreakMaskChain": false
}